datahub_airflow_plugin/__init__.py
datahub_airflow_plugin/_airflow_compat.py
datahub_airflow_plugin/_airflow_shims.py
datahub_airflow_plugin/_config.py
datahub_airflow_plugin/_datahub_listener_module.py
datahub_airflow_plugin/_datahub_ol_adapter.py
datahub_airflow_plugin/_extractors.py
datahub_airflow_plugin/datahub_listener.py
datahub_airflow_plugin/datahub_plugin.py
datahub_airflow_plugin/datahub_plugin_v22.py
datahub_airflow_plugin/entities.py
datahub_airflow_plugin/py.typed
datahub_airflow_plugin/client/__init__.py
datahub_airflow_plugin/client/airflow_generator.py
datahub_airflow_plugin/example_dags/__init__.py
datahub_airflow_plugin/example_dags/generic_recipe_sample_dag.py
datahub_airflow_plugin/example_dags/graph_usage_sample_dag.py
datahub_airflow_plugin/example_dags/lineage_backend_demo.py
datahub_airflow_plugin/example_dags/lineage_backend_taskflow_demo.py
datahub_airflow_plugin/example_dags/lineage_emission_dag.py
datahub_airflow_plugin/example_dags/mysql_sample_dag.py
datahub_airflow_plugin/example_dags/snowflake_sample_dag.py
datahub_airflow_plugin/hooks/__init__.py
datahub_airflow_plugin/hooks/datahub.py
datahub_airflow_plugin/lineage/__init__.py
datahub_airflow_plugin/lineage/_lineage_core.py
datahub_airflow_plugin/lineage/datahub.py
datahub_airflow_plugin/operators/__init__.py
datahub_airflow_plugin/operators/datahub.py
datahub_airflow_plugin/operators/datahub_assertion_operator.py
datahub_airflow_plugin/operators/datahub_assertion_sensor.py
datahub_airflow_plugin/operators/datahub_operation_operator.py
datahub_airflow_plugin/operators/datahub_operation_sensor.py
acryl_datahub_airflow_plugin-15.0.4.dist-info/METADATA
acryl_datahub_airflow_plugin-15.0.4.dist-info/WHEEL
acryl_datahub_airflow_plugin-15.0.4.dist-info/entry_points.txt
acryl_datahub_airflow_plugin-15.0.4.dist-info/top_level.txt
acryl_datahub_airflow_plugin-15.0.4.dist-info/RECORD
